{
  "orgAppHeaders": {
  	"Log Number": "logNo",
    "Title": "title",
    "Program": "program",
    "Principal Investigator": "piFullname",
    "Pre-App Due Date": "preDueDate",
    "Pre-App Status": "preStatus",
    "Full-App Due Date": "fullDueDate",
    "Full-App Status": "fullStatus",
    "Award Number": "awardNumber"
  },
  "myAppHeaders": {
    "Log Number": "logno",
    "Title": "title",
    "Pre-App Due Date": "preDueDate",
    "Pre-App Status": "preStatus",
    "Full-App Due Date": "fullDueDate",
    "Full-App Status": "fullStatus",
    "Award Number": "awardNumber"
  },
  "singleAppHeaders": {
    "File Name": "filename",
    "File Type": "filetype",
    "File Size (bytes)": "filesize",
    "Uploaded By": "uploadedBy",
    "Uploaded On": "uploadedOn",
    "Action": "action"
  },
  "statusGroups": {
    "Pre-App Status": [
      {"value": "PreApp-DRAFT", "label": "Draft"},
      {"value": "PreApp-Submitted", "label": "Submitted"},
      {"value": "PreApp-DELETED", "label": "Deleted"},
      {"value": "PreApp-WITHDRAWN", "label": "Withdrawn"}],
    "Full-App Status": [
      {"value": "FullApp-DRAFT", "label": "Draft"},
      {"value": "FullApp-VERIFIED", "label": "Verified"},
      {"value": "FullApp-WITHDRAWN", "label": "Withdrawn"},
      {"value": "FullApp-BO_APPROVAL_PENDING", "label": "Business Official Approval Pending"},
      {"value": "FullApp-BO_RETURN_TO_PI", "label": "Business Official Return to PI"},
      {"value": "FullApp-BO_APPROVED", "label": "Business Official Approved"},
      {"value": "FullApp-BO_NOT_APPROVED", "label": "Business Official Not Approved"}],
    "Funding Status": [
      {"value": "Funded", "label": "Funded"}
    ]
  },
  "fileTypes": [
    {
      "label": "Federal Financial Report (SF-425)",
      "value": "FFR"
    }
  ]
}
